MANIFEST.in
README.md
setup.py
lifebrick/__init__.py
lifebrick/__version__.py
lifebrick/cli.py
lifebrick/exceptions.py
lifebrick/help.py
lifebrick/models.py
lifebrick/static.py
lifebrick/status_codes.py
lifebrick/utils.py
lifebrick.egg-info/PKG-INFO
lifebrick.egg-info/SOURCES.txt
lifebrick.egg-info/dependency_links.txt
lifebrick.egg-info/entry_points.txt
lifebrick.egg-info/not-zip-safe
lifebrick.egg-info/requires.txt
lifebrick.egg-info/top_level.txt
lifebrick/data/.DS_Store
lifebrick/data/GeoLite2-City.mmdb
lifebrick/data/GeoLite2-Country.mmdb
lifebrick/data/iso3166.csv